thunkmetrc/__init__.py
thunkmetrc/inventory.py
thunkmetrc-0.2.2.dist-info/METADATA
thunkmetrc-0.2.2.dist-info/WHEEL
thunkmetrc-0.2.2.dist-info/RECORD
