Metadata-Version: 2.4
Name: thunkmetrc
Version: 0.2.2
Summary: High-level ThunkMetrc Python SDK
License-Expression: MIT
Requires-Python: >=3.10
Requires-Dist: python-dateutil>=2.8.2
Requires-Dist: thunkmetrc-wrapper==0.2.2
